LICENSE
README.rst
setup.py
actomyosin_analyser/__init__.py
actomyosin_analyser/_version.py
actomyosin_analyser.egg-info/PKG-INFO
actomyosin_analyser.egg-info/SOURCES.txt
actomyosin_analyser.egg-info/dependency_links.txt
actomyosin_analyser.egg-info/entry_points.txt
actomyosin_analyser.egg-info/not-zip-safe
actomyosin_analyser.egg-info/requires.txt
actomyosin_analyser.egg-info/top_level.txt
actomyosin_analyser/analysis/__init__.py
actomyosin_analyser/analysis/abstract_analyser.py
actomyosin_analyser/analysis/analyser.py
actomyosin_analyser/analysis/filament_center_of_mass.py
actomyosin_analyser/analysis/geometry.py
actomyosin_analyser/analysis/mean_squared_displacement.py
actomyosin_analyser/analysis/periodic_boundaries.py
actomyosin_analyser/analysis/polymer_density.py
actomyosin_analyser/analysis/microrheology/__init__.py
actomyosin_analyser/analysis/microrheology/mason_method.py
actomyosin_analyser/analysis/microrheology/paust_method.py
actomyosin_analyser/analysis/microrheology/plateau_modulus.py
actomyosin_analyser/analysis/persistence_length/__init__.py
actomyosin_analyser/analysis/persistence_length/approx_becker_2010.py
actomyosin_analyser/file_io/__init__.py
actomyosin_analyser/file_io/chunky_text_stack_converter.py
actomyosin_analyser/file_io/config_reader.py
actomyosin_analyser/file_io/config_reader_beads.py
actomyosin_analyser/file_io/data_reader.py
actomyosin_analyser/file_io/filament_data_reader.py
actomyosin_analyser/file_io/segment_data_reader.py
actomyosin_analyser/file_io/state_exporter.py
actomyosin_analyser/file_io/tables.py
actomyosin_analyser/file_io/text_bead_data_reader.py
actomyosin_analyser/file_io/text_stack_converter.py
actomyosin_analyser/file_io/text_stack_reader.py
actomyosin_analyser/file_io/xyz_exporter.py
actomyosin_analyser/model/__init__.py
actomyosin_analyser/model/bead.py
actomyosin_analyser/model/bead_states.py
actomyosin_analyser/pipelines/__init__.py
actomyosin_analyser/pipelines/_pipeline.py
actomyosin_analyser/pipelines/end_to_end_distance.py
actomyosin_analyser/pipelines/energy.py
actomyosin_analyser/pipelines/length_distribution.py
actomyosin_analyser/pipelines/polymer_density.py
actomyosin_analyser/pipelines/segment_length.py
actomyosin_analyser/pipelines/time.py
