Metadata-Version: 2.1
Name: actomyosin-analyser
Version: 1.18.11
Summary: Analysis tools for actomyosin data
Home-page: UNKNOWN
Author: Ilyas Kuhlemann
Author-email: ilyasp.ku@gmail.com
License: GPLv3
Platform: UNKNOWN
License-File: LICENSE
